pyside_settings_manager/__init__.py
pyside_settings_manager/settings.py
pyside_settings_manager-0.0.23.dist-info/licenses/LICENSE
pyside_settings_manager-0.0.23.dist-info/WHEEL
pyside_settings_manager-0.0.23.dist-info/METADATA
pyside_settings_manager-0.0.23.dist-info/RECORD
