Metadata-Version: 2.4
Name: pyside-settings-manager
Version: 0.0.23
Summary: A simple settings manager for PySide6
Author-email: Daniel Castro <danicc097@gmail.com>
Requires-Python: >=3.11
Classifier: Programming Language :: Python :: 3
Classifier: License :: OSI Approved :: Apache Software License
Classifier: Operating System :: OS Independent
License-File: LICENSE
Requires-Dist: pyside6>=6.9.0
Project-URL: Bug Tracker, https://github.com/danicc097/pyside-settings-manager/issues
Project-URL: Homepage, https://github.com/danicc097/pyside-settings-manager
Project-URL: Source, https://github.com/danicc097/pyside-settings-manager
